pushdit/__init__.py
pushdit/pushit.py
pushit/__init__.py
pushit/pushit.py
pushdit-0.0.7.dist-info/LICENSE
pushdit-0.0.7.dist-info/METADATA
pushdit-0.0.7.dist-info/WHEEL
pushdit-0.0.7.dist-info/top_level.txt
pushdit-0.0.7.dist-info/RECORD
