Metadata-Version: 2.1
Name: pushdit
Version: 0.0.7
Summary: pushd command like Linux
Home-page: https://github.com/Antsthebul/pushdit
Author: Antsthebul
Author-email: anthony.allen.srt@gmail.com
License: UNKNOWN
Platform: UNKNOWN
Classifier: Programming Language :: Python :: 3
Classifier: License :: OSI Approved :: GNU General Public License (GPL)
Classifier: Operating System :: OS Independent
